bitcoin/__init__.py
bitcoin/address.py
bitcoin/authtree.py
bitcoin/base58.py
bitcoin/core.py
bitcoin/crypto.py
bitcoin/defaults.py
bitcoin/destination.py
bitcoin/ecdsa__common.py
bitcoin/ecdsa_generic.py
bitcoin/ecdsa_openssl.py
bitcoin/errors.py
bitcoin/hash.py
bitcoin/ledger.py
bitcoin/merkle.py
bitcoin/mixins.py
bitcoin/numeric.py
bitcoin/rpc.py
bitcoin/script.py
bitcoin/serialize.py
bitcoin/tools.py
python_bitcoin-0.0.15.dist-info/AUTHORS.md
python_bitcoin-0.0.15.dist-info/LICENSE.md
python_bitcoin-0.0.15.dist-info/METADATA
python_bitcoin-0.0.15.dist-info/WHEEL
python_bitcoin-0.0.15.dist-info/top_level.txt
python_bitcoin-0.0.15.dist-info/RECORD
